{"ilp-kit.michielbdejong.com":{"pineapplesheep.ilp.rocks":{"error":{},"duration":3121},"hive.dennisappelt.com":{"error":{},"duration":3160},"john.jpvbs.com":{"error":{},"duration":3401},"nexus.justmoon.com":{"error":{},"duration":3735},"michiel-is-not-available.herokuapp.com":{"error":{},"duration":3823},"cygnus.vahehovhannisyan.com":{"error":{},"duration":3870},"cornelius.sharafian.com":{"error":{},"duration":4110},"ggizi.herokuapp.com":{"error":{},"duration":4094},"royalcrypto.com":{"error":{},"duration":4344},"best-ilp.herokuapp.com":{"error":{},"duration":4383},"someledger.herokuapp.com":{"error":{},"duration":10000},"ilp-kit.michielbdejong.com":{"error":{},"duration":12845}},"hive.dennisappelt.com":{"ilp-kit.michielbdejong.com":{"error":{},"duration":3319},"pineapplesheep.ilp.rocks":{"error":{},"duration":3643},"michiel-is-not-available.herokuapp.com":{"error":{},"duration":4060},"royalcrypto.com":{"error":{},"duration":4553},"best-ilp.herokuapp.com":{"error":{},"duration":4606},"john.jpvbs.com":{"error":{"name":"NotAcceptedError"},"duration":5258},"cygnus.vahehovhannisyan.com":{"error":{"name":"NotAcceptedError"},"duration":5773},"ggizi.herokuapp.com":{"fee":0,"duration":6867},"someledger.herokuapp.com":{"error":{},"duration":10013},"hive.dennisappelt.com":{"error":{},"duration":13120},"cornelius.sharafian.com":{"error":{},"duration":14912},"nexus.justmoon.com":{"error":{},"duration":15542}},"pineapplesheep.ilp.rocks":{"pineapplesheep.ilp.rocks":{"error":{"name":"NotAcceptedError"},"duration":3383},"ilp-kit.michielbdejong.com":{"error":{},"duration":3619},"hive.dennisappelt.com":{"error":{"name":"NotAcceptedError"},"duration":3754},"michiel-is-not-available.herokuapp.com":{"error":{},"duration":3984},"royalcrypto.com":{"error":{},"duration":4501},"best-ilp.herokuapp.com":{"error":{},"duration":4579},"ggizi.herokuapp.com":{"error":{"name":"NotAcceptedError"},"duration":5135},"john.jpvbs.com":{"error":{"name":"NotAcceptedError"},"duration":5171},"nexus.justmoon.com":{"error":{"name":"NotAcceptedError"},"duration":5350},"cygnus.vahehovhannisyan.com":{"error":{"name":"NotAcceptedError"},"duration":5630},"cornelius.sharafian.com":{"error":{"name":"NotAcceptedError"},"duration":5691},"someledger.herokuapp.com":{"error":{},"duration":10002}},"nexus.justmoon.com":{"hive.dennisappelt.com":{"error":{},"duration":3827},"john.jpvbs.com":{"error":{},"duration":3994},"ilp-kit.michielbdejong.com":{"error":{},"duration":4126},"pineapplesheep.ilp.rocks":{"error":{},"duration":4345},"cygnus.vahehovhannisyan.com":{"error":{},"duration":4399},"michiel-is-not-available.herokuapp.com":{"error":{},"duration":4488},"royalcrypto.com":{"error":{},"duration":4748},"cornelius.sharafian.com":{"error":{},"duration":4807},"ggizi.herokuapp.com":{"error":{},"duration":4817},"best-ilp.herokuapp.com":{"error":{},"duration":5196},"someledger.herokuapp.com":{"error":{},"duration":10024},"nexus.justmoon.com":{"error":{},"duration":14281}},"cygnus.vahehovhannisyan.com":{"ilp-kit.michielbdejong.com":{"error":{},"duration":3863},"hive.dennisappelt.com":{"error":{},"duration":3893},"pineapplesheep.ilp.rocks":{"error":{},"duration":4037},"john.jpvbs.com":{"error":{},"duration":4262},"michiel-is-not-available.herokuapp.com":{"error":{},"duration":4417},"nexus.justmoon.com":{"error":{},"duration":4430},"cornelius.sharafian.com":{"error":{},"duration":4742},"ggizi.herokuapp.com":{"error":{},"duration":4901},"royalcrypto.com":{"error":{},"duration":5028},"best-ilp.herokuapp.com":{"error":{},"duration":5049},"someledger.herokuapp.com":{"error":{},"duration":10006},"cygnus.vahehovhannisyan.com":{"error":{},"duration":14276}},"michiel-is-not-available.herokuapp.com":{"pineapplesheep.ilp.rocks":{"error":{},"duration":3968},"ilp-kit.michielbdejong.com":{"error":{},"duration":4094},"michiel-is-not-available.herokuapp.com":{"error":{"name":"NotAcceptedError"},"duration":4187},"hive.dennisappelt.com":{"error":{},"duration":4217},"john.jpvbs.com":{"error":{},"duration":4285},"nexus.justmoon.com":{"error":{},"duration":4339},"cygnus.vahehovhannisyan.com":{"error":{},"duration":4378},"ggizi.herokuapp.com":{"error":{},"duration":4620},"cornelius.sharafian.com":{"error":{},"duration":4674},"royalcrypto.com":{"error":{},"duration":4789},"best-ilp.herokuapp.com":{"error":{},"duration":4806},"someledger.herokuapp.com":{"error":{},"duration":10005}},"john.jpvbs.com":{"pineapplesheep.ilp.rocks":{"error":{},"duration":4207},"michiel-is-not-available.herokuapp.com":{"error":{},"duration":4433},"royalcrypto.com":{"error":{},"duration":4773},"best-ilp.herokuapp.com":{"error":{},"duration":4910},"cygnus.vahehovhannisyan.com":{"error":{"name":"NotAcceptedError"},"duration":6175},"ilp-kit.michielbdejong.com":{"error":{},"duration":8972},"ggizi.herokuapp.com":{"fee":1,"duration":9684},"someledger.herokuapp.com":{"error":{},"duration":10001},"john.jpvbs.com":{"error":{},"duration":13739},"cornelius.sharafian.com":{"error":{},"duration":15133},"hive.dennisappelt.com":{"error":{},"duration":15446},"nexus.justmoon.com":{"error":{},"duration":15765}},"cornelius.sharafian.com":{"hive.dennisappelt.com":{"error":{},"duration":4360},"ilp-kit.michielbdejong.com":{"error":{},"duration":4540},"pineapplesheep.ilp.rocks":{"error":{},"duration":4540},"cygnus.vahehovhannisyan.com":{"error":{},"duration":4658},"nexus.justmoon.com":{"error":{},"duration":4848},"john.jpvbs.com":{"error":{},"duration":5045},"michiel-is-not-available.herokuapp.com":{"error":{},"duration":5052},"ggizi.herokuapp.com":{"error":{},"duration":5271},"best-ilp.herokuapp.com":{"error":{},"duration":5442},"royalcrypto.com":{"error":{},"duration":5569},"someledger.herokuapp.com":{"error":{},"duration":10005},"cornelius.sharafian.com":{"error":{},"duration":14718}},"ggizi.herokuapp.com":{"ilp-kit.michielbdejong.com":{"error":{},"duration":4514},"pineapplesheep.ilp.rocks":{"error":{},"duration":4634},"michiel-is-not-available.herokuapp.com":{"error":{},"duration":4943},"royalcrypto.com":{"error":{},"duration":5411},"best-ilp.herokuapp.com":{"error":{},"duration":5462},"hive.dennisappelt.com":{"error":{"name":"NotAcceptedError"},"duration":5686},"john.jpvbs.com":{"error":{"name":"NotAcceptedError"},"duration":7186},"someledger.herokuapp.com":{"error":{},"duration":10001},"ggizi.herokuapp.com":{"error":{},"duration":14807},"cornelius.sharafian.com":{"error":{},"duration":16422},"nexus.justmoon.com":{"error":{},"duration":16523},"cygnus.vahehovhannisyan.com":{"error":{},"duration":16922}},"best-ilp.herokuapp.com":{"ilp-kit.michielbdejong.com":{"error":{},"duration":4755},"pineapplesheep.ilp.rocks":{"error":{},"duration":4953},"michiel-is-not-available.herokuapp.com":{"error":{},"duration":5004},"best-ilp.herokuapp.com":{"error":{"name":"NotAcceptedError"},"duration":5537},"royalcrypto.com":{"error":{},"duration":5550},"john.jpvbs.com":{"error":{"name":"NotAcceptedError"},"duration":6018},"nexus.justmoon.com":{"error":{"name":"NotAcceptedError"},"duration":6841},"hive.dennisappelt.com":{"error":{"name":"NotAcceptedError"},"duration":7234},"cygnus.vahehovhannisyan.com":{"error":{"name":"NotAcceptedError"},"duration":7241},"cornelius.sharafian.com":{"error":{"name":"NotAcceptedError"},"duration":7270},"ggizi.herokuapp.com":{"error":{"name":"NotAcceptedError"},"duration":7709},"someledger.herokuapp.com":{"error":{},"duration":10001}},"royalcrypto.com":{"royalcrypto.com":{"error":{"name":"NotAcceptedError"},"duration":5700},"ilp-kit.michielbdejong.com":{"error":{},"duration":9936},"hive.dennisappelt.com":{"error":{},"duration":9959},"john.jpvbs.com":{"error":{},"duration":9974},"pineapplesheep.ilp.rocks":{"error":{},"duration":10016},"someledger.herokuapp.com":{"error":{},"duration":10016},"michiel-is-not-available.herokuapp.com":{"error":{},"duration":14755},"cygnus.vahehovhannisyan.com":{"error":{},"duration":14783},"cornelius.sharafian.com":{"error":{},"duration":14913},"ggizi.herokuapp.com":{"error":{},"duration":14971},"best-ilp.herokuapp.com":{"error":{},"duration":15248},"nexus.justmoon.com":{"error":{},"duration":15470}},"someledger.herokuapp.com":{"someledger.herokuapp.com":{"error":{},"duration":10001},"hive.dennisappelt.com":{"error":{},"duration":52902},"ilp-kit.michielbdejong.com":{"error":{},"duration":52924},"john.jpvbs.com":{"error":{},"duration":52978},"pineapplesheep.ilp.rocks":{"error":{},"duration":52984},"nexus.justmoon.com":{"error":{},"duration":53302},"michiel-is-not-available.herokuapp.com":{"error":{},"duration":53302},"cygnus.vahehovhannisyan.com":{"error":{},"duration":53433},"cornelius.sharafian.com":{"error":{},"duration":53620},"ggizi.herokuapp.com":{"error":{},"duration":53727},"royalcrypto.com":{"error":{},"duration":54022},"best-ilp.herokuapp.com":{"error":{},"duration":54029}}}