{"ilp-kit.michielbdejong.com":{"pineapplesheep.ilp.rocks":{"error":{},"duration":2958},"hive.dennisappelt.com":{"error":{},"duration":3216},"cygnus.vahehovhannisyan.com":{"error":{},"duration":3626},"michiel-is-not-available.herokuapp.com":{"error":{},"duration":3797},"nexus.justmoon.com":{"error":{},"duration":3841},"john.jpvbs.com":{"error":{},"duration":3897},"cornelius.sharafian.com":{"error":{},"duration":3922},"ggizi.herokuapp.com":{"error":{},"duration":4090},"royalcrypto.com":{"error":{},"duration":4220},"best-ilp.herokuapp.com":{"error":{},"duration":4256},"someledger.herokuapp.com":{"error":{},"duration":10001},"ilp-kit.michielbdejong.com":{"error":{},"duration":12726}},"hive.dennisappelt.com":{"ilp-kit.michielbdejong.com":{"error":{},"duration":3299},"pineapplesheep.ilp.rocks":{"error":{},"duration":3413},"michiel-is-not-available.herokuapp.com":{"error":{},"duration":3800},"royalcrypto.com":{"error":{},"duration":4421},"best-ilp.herokuapp.com":{"error":{},"duration":5100},"ggizi.herokuapp.com":{"error":{"name":"NotAcceptedError"},"duration":5357},"nexus.justmoon.com":{"error":{"name":"NotAcceptedError"},"duration":5619},"someledger.herokuapp.com":{"error":{},"duration":10001},"hive.dennisappelt.com":{"error":{},"duration":12911},"cornelius.sharafian.com":{"error":{},"duration":14965},"cygnus.vahehovhannisyan.com":{"error":{},"duration":15243},"john.jpvbs.com":{"error":{},"duration":15595}},"pineapplesheep.ilp.rocks":{"ilp-kit.michielbdejong.com":{"error":{},"duration":3318},"pineapplesheep.ilp.rocks":{"error":{"name":"NotAcceptedError"},"duration":3341},"michiel-is-not-available.herokuapp.com":{"error":{},"duration":3739},"hive.dennisappelt.com":{"error":{"name":"NotAcceptedError"},"duration":3949},"best-ilp.herokuapp.com":{"error":{},"duration":4473},"royalcrypto.com":{"error":{},"duration":4541},"cygnus.vahehovhannisyan.com":{"error":{"name":"NotAcceptedError"},"duration":5093},"ggizi.herokuapp.com":{"error":{"name":"NotAcceptedError"},"duration":5299},"cornelius.sharafian.com":{"error":{"name":"NotAcceptedError"},"duration":5332},"nexus.justmoon.com":{"error":{"name":"NotAcceptedError"},"duration":5621},"john.jpvbs.com":{"error":{"name":"NotAcceptedError"},"duration":5811},"someledger.herokuapp.com":{"error":{},"duration":10000}},"michiel-is-not-available.herokuapp.com":{"ilp-kit.michielbdejong.com":{"error":{},"duration":3705},"pineapplesheep.ilp.rocks":{"error":{},"duration":3860},"hive.dennisappelt.com":{"error":{},"duration":3939},"michiel-is-not-available.herokuapp.com":{"error":{"name":"NotAcceptedError"},"duration":3996},"cygnus.vahehovhannisyan.com":{"error":{},"duration":4243},"john.jpvbs.com":{"error":{},"duration":4267},"nexus.justmoon.com":{"error":{},"duration":4311},"cornelius.sharafian.com":{"error":{},"duration":4374},"ggizi.herokuapp.com":{"error":{},"duration":4552},"royalcrypto.com":{"error":{},"duration":4673},"best-ilp.herokuapp.com":{"error":{},"duration":4723},"someledger.herokuapp.com":{"error":{},"duration":10001}},"nexus.justmoon.com":{"pineapplesheep.ilp.rocks":{"error":{},"duration":3816},"ilp-kit.michielbdejong.com":{"error":{},"duration":4046},"hive.dennisappelt.com":{"error":{},"duration":4201},"cygnus.vahehovhannisyan.com":{"error":{},"duration":4208},"cornelius.sharafian.com":{"error":{},"duration":4578},"michiel-is-not-available.herokuapp.com":{"error":{},"duration":4587},"john.jpvbs.com":{"error":{},"duration":4593},"ggizi.herokuapp.com":{"error":{},"duration":5026},"best-ilp.herokuapp.com":{"error":{},"duration":5028},"royalcrypto.com":{"error":{},"duration":5443},"someledger.herokuapp.com":{"error":{},"duration":10001},"nexus.justmoon.com":{"error":{},"duration":14728}},"cygnus.vahehovhannisyan.com":{"hive.dennisappelt.com":{"error":{},"duration":3877},"ilp-kit.michielbdejong.com":{"error":{},"duration":3935},"michiel-is-not-available.herokuapp.com":{"error":{},"duration":4069},"pineapplesheep.ilp.rocks":{"error":{},"duration":4179},"john.jpvbs.com":{"error":{},"duration":4310},"nexus.justmoon.com":{"error":{},"duration":4323},"cornelius.sharafian.com":{"error":{},"duration":4473},"ggizi.herokuapp.com":{"error":{},"duration":4624},"royalcrypto.com":{"error":{},"duration":4908},"best-ilp.herokuapp.com":{"error":{},"duration":5015},"someledger.herokuapp.com":{"error":{},"duration":10001},"cygnus.vahehovhannisyan.com":{"error":{},"duration":13941}},"cornelius.sharafian.com":{"pineapplesheep.ilp.rocks":{"error":{},"duration":4062},"ilp-kit.michielbdejong.com":{"error":{},"duration":4255},"hive.dennisappelt.com":{"error":{},"duration":4419},"nexus.justmoon.com":{"error":{},"duration":4523},"cygnus.vahehovhannisyan.com":{"error":{},"duration":4627},"michiel-is-not-available.herokuapp.com":{"error":{},"duration":4713},"john.jpvbs.com":{"error":{},"duration":5035},"ggizi.herokuapp.com":{"error":{},"duration":5213},"royalcrypto.com":{"error":{},"duration":5553},"best-ilp.herokuapp.com":{"error":{},"duration":5853},"someledger.herokuapp.com":{"error":{},"duration":10001},"cornelius.sharafian.com":{"error":{},"duration":14543}},"john.jpvbs.com":{"ilp-kit.michielbdejong.com":{"error":{},"duration":4238},"pineapplesheep.ilp.rocks":{"error":{},"duration":4475},"michiel-is-not-available.herokuapp.com":{"error":{},"duration":4537},"best-ilp.herokuapp.com":{"error":{},"duration":4964},"royalcrypto.com":{"error":{},"duration":5117},"nexus.justmoon.com":{"error":{"name":"NotAcceptedError"},"duration":5989},"hive.dennisappelt.com":{"error":{"name":"NotAcceptedError"},"duration":5999},"cygnus.vahehovhannisyan.com":{"error":{"name":"NotAcceptedError"},"duration":5999},"ggizi.herokuapp.com":{"fee":1,"duration":9749},"someledger.herokuapp.com":{"error":{},"duration":10001},"john.jpvbs.com":{"error":{},"duration":13902},"cornelius.sharafian.com":{"error":{},"duration":15263}},"ggizi.herokuapp.com":{"ilp-kit.michielbdejong.com":{"error":{},"duration":4482},"pineapplesheep.ilp.rocks":{"error":{},"duration":4540},"michiel-is-not-available.herokuapp.com":{"error":{},"duration":4609},"royalcrypto.com":{"error":{},"duration":5628},"best-ilp.herokuapp.com":{"error":{},"duration":5735},"john.jpvbs.com":{"error":{"name":"NotAcceptedError"},"duration":6787},"cornelius.sharafian.com":{"error":{"name":"NotAcceptedError"},"duration":6850},"cygnus.vahehovhannisyan.com":{"error":{"name":"NotAcceptedError"},"duration":7055},"hive.dennisappelt.com":{"fee":1,"duration":7069},"nexus.justmoon.com":{"error":{"name":"NotAcceptedError"},"duration":7398},"someledger.herokuapp.com":{"error":{},"duration":10001},"ggizi.herokuapp.com":{"error":{},"duration":14889}},"royalcrypto.com":{"hive.dennisappelt.com":{"error":{},"duration":4752},"ilp-kit.michielbdejong.com":{"error":{},"duration":4771},"pineapplesheep.ilp.rocks":{"error":{},"duration":4779},"michiel-is-not-available.herokuapp.com":{"error":{},"duration":4890},"cygnus.vahehovhannisyan.com":{"error":{},"duration":5108},"john.jpvbs.com":{"error":{},"duration":5174},"nexus.justmoon.com":{"error":{},"duration":5386},"cornelius.sharafian.com":{"error":{},"duration":5486},"ggizi.herokuapp.com":{"error":{},"duration":5531},"royalcrypto.com":{"error":{"name":"NotAcceptedError"},"duration":5941},"best-ilp.herokuapp.com":{"error":{},"duration":5999},"someledger.herokuapp.com":{"error":{},"duration":10001}},"best-ilp.herokuapp.com":{"ilp-kit.michielbdejong.com":{"error":{},"duration":4900},"pineapplesheep.ilp.rocks":{"error":{},"duration":5198},"michiel-is-not-available.herokuapp.com":{"error":{},"duration":5271},"royalcrypto.com":{"error":{},"duration":5790},"john.jpvbs.com":{"error":{"name":"NotAcceptedError"},"duration":6830},"hive.dennisappelt.com":{"error":{"name":"NotAcceptedError"},"duration":7833},"cygnus.vahehovhannisyan.com":{"error":{"name":"NotAcceptedError"},"duration":7839},"nexus.justmoon.com":{"error":{"name":"NotAcceptedError"},"duration":7863},"ggizi.herokuapp.com":{"error":{"name":"NotAcceptedError"},"duration":8036},"someledger.herokuapp.com":{"error":{},"duration":10001},"best-ilp.herokuapp.com":{"error":{},"duration":15667},"cornelius.sharafian.com":{"error":{},"duration":17062}},"someledger.herokuapp.com":{"someledger.herokuapp.com":{"error":{},"duration":10001},"ilp-kit.michielbdejong.com":{"error":{},"duration":52606},"pineapplesheep.ilp.rocks":{"error":{},"duration":52766},"hive.dennisappelt.com":{"error":{},"duration":52838},"michiel-is-not-available.herokuapp.com":{"error":{},"duration":53022},"john.jpvbs.com":{"error":{},"duration":53158},"cygnus.vahehovhannisyan.com":{"error":{},"duration":53194},"nexus.justmoon.com":{"error":{},"duration":53315},"ggizi.herokuapp.com":{"error":{},"duration":53703},"cornelius.sharafian.com":{"error":{},"duration":54022},"royalcrypto.com":{"error":{},"duration":54249},"best-ilp.herokuapp.com":{"error":{},"duration":54292}}}