{"john.jpvbs.com":{"ilp-kit.michielbdejong.com":{"error":{},"duration":2930},"michiel-eur.herokuapp.com":{"error":{},"duration":3502},"michiel-is-not-available.herokuapp.com":{"error":{},"duration":3713},"nexus.justmoon.com":{"error":{},"duration":3896},"cygnus.vahehovhannisyan.com":{"error":{},"duration":4074},"ggizi.herokuapp.com":{"error":{},"duration":5037},"hive.dennisappelt.com":{"fee":1,"duration":6754},"cornelius.sharafian.com":{"fee":1,"duration":9012}},"michiel-is-not-available.herokuapp.com":{"ilp-kit.michielbdejong.com":{"error":{},"duration":2964},"hive.dennisappelt.com":{"error":{},"duration":3079},"john.jpvbs.com":{"error":{},"duration":3652},"cygnus.vahehovhannisyan.com":{"error":{},"duration":3970},"michiel-eur.herokuapp.com":{"error":{"name":"NotAcceptedError"},"duration":4090},"nexus.justmoon.com":{"error":{},"duration":4433},"cornelius.sharafian.com":{"error":{},"duration":4628},"ggizi.herokuapp.com":{"error":{},"duration":4954}},"cygnus.vahehovhannisyan.com":{"ilp-kit.michielbdejong.com":{"error":{},"duration":3327},"hive.dennisappelt.com":{"error":{},"duration":3339},"nexus.justmoon.com":{"error":{},"duration":3817},"michiel-eur.herokuapp.com":{"error":{},"duration":3970},"michiel-is-not-available.herokuapp.com":{"error":{},"duration":4042},"john.jpvbs.com":{"error":{},"duration":4255},"cornelius.sharafian.com":{"error":{},"duration":4820},"ggizi.herokuapp.com":{"error":{},"duration":5120}},"ilp-kit.michielbdejong.com":{"michiel-is-not-available.herokuapp.com":{"error":{"name":"NotAcceptedError"},"duration":3571},"nexus.justmoon.com":{"error":{"name":"NotAcceptedError"},"duration":4533},"cornelius.sharafian.com":{"error":{"name":"NotAcceptedError"},"duration":4789},"john.jpvbs.com":{"fee":-0.05632295700000005,"duration":5550},"hive.dennisappelt.com":{"error":{},"duration":12964},"michiel-eur.herokuapp.com":{"error":{},"duration":13276},"cygnus.vahehovhannisyan.com":{"error":{},"duration":13755},"ggizi.herokuapp.com":{"error":{},"duration":15220}},"michiel-eur.herokuapp.com":{"hive.dennisappelt.com":{"error":{"name":"NotAcceptedError"},"duration":4296},"michiel-is-not-available.herokuapp.com":{"error":{"name":"NotAcceptedError"},"duration":4293},"ilp-kit.michielbdejong.com":{"error":{"name":"AlreadyRolledBackError"},"duration":4622},"cygnus.vahehovhannisyan.com":{"error":{"name":"NotAcceptedError"},"duration":4732},"nexus.justmoon.com":{"error":{"name":"NotAcceptedError"},"duration":4735},"cornelius.sharafian.com":{"fee":0,"duration":5867},"john.jpvbs.com":{"error":{},"duration":14274},"ggizi.herokuapp.com":{"error":{},"duration":14984}},"ggizi.herokuapp.com":{"hive.dennisappelt.com":{"error":{"name":"NotAcceptedError"},"duration":6112},"ilp-kit.michielbdejong.com":{"error":{"name":"NotAcceptedError"},"duration":6139},"michiel-eur.herokuapp.com":{"error":{"name":"NotAcceptedError"},"duration":6339},"michiel-is-not-available.herokuapp.com":{"error":{"name":"NotAcceptedError"},"duration":6369},"cornelius.sharafian.com":{"error":{"name":"NotAcceptedError"},"duration":6480},"nexus.justmoon.com":{"error":{"name":"NotAcceptedError"},"duration":6493},"cygnus.vahehovhannisyan.com":{"fee":1,"duration":8399},"john.jpvbs.com":{"error":{},"duration":15805}},"hive.dennisappelt.com":{"ilp-kit.michielbdejong.com":{"error":{},"duration":12574},"michiel-is-not-available.herokuapp.com":{"error":{},"duration":12863},"michiel-eur.herokuapp.com":{"error":{},"duration":13086},"nexus.justmoon.com":{"error":{},"duration":13492},"cygnus.vahehovhannisyan.com":{"error":{},"duration":13919},"john.jpvbs.com":{"error":{},"duration":14212},"ggizi.herokuapp.com":{"error":{},"duration":14894},"cornelius.sharafian.com":{"error":{},"duration":15520}},"nexus.justmoon.com":{"michiel-eur.herokuapp.com":{"error":{},"duration":13285},"ilp-kit.michielbdejong.com":{"error":{},"duration":13766},"michiel-is-not-available.herokuapp.com":{"error":{},"duration":13886},"cygnus.vahehovhannisyan.com":{"error":{},"duration":14021},"hive.dennisappelt.com":{"error":{},"duration":14084},"john.jpvbs.com":{"error":{},"duration":14345},"cornelius.sharafian.com":{"error":{},"duration":14952},"ggizi.herokuapp.com":{"error":{},"duration":14966}},"cornelius.sharafian.com":{"ilp-kit.michielbdejong.com":{"error":{},"duration":13597},"hive.dennisappelt.com":{"error":{},"duration":13893},"michiel-is-not-available.herokuapp.com":{"error":{},"duration":13935},"john.jpvbs.com":{"error":{},"duration":14140},"michiel-eur.herokuapp.com":{"error":{},"duration":14295},"nexus.justmoon.com":{"error":{},"duration":14459},"cygnus.vahehovhannisyan.com":{"error":{},"duration":14479},"ggizi.herokuapp.com":{"error":{},"duration":15258}}}