{"pineapplesheep.ilp.rocks":{"ilp-kit.michielbdejong.com":{"error":{},"duration":4510},"pineapplesheep.ilp.rocks":{"error":{"name":"NotAcceptedError"},"duration":4639},"michiel-is-not-available.herokuapp.com":{"error":{},"duration":5075},"michiel-eur.herokuapp.com":{"error":{},"duration":5869},"hive.dennisappelt.com":{"error":{"name":"NotAcceptedError"},"duration":6080},"best-ilp.herokuapp.com":{"error":{},"duration":6538},"nexus.justmoon.com":{"error":{"name":"NotAcceptedError"},"duration":7576},"cornelius.sharafian.com":{"error":{"name":"NotAcceptedError"},"duration":7748},"royalcrypto.com":{"error":{},"duration":7829},"ggizi.herokuapp.com":{"error":{"name":"NotAcceptedError"},"duration":8127},"cygnus.vahehovhannisyan.com":{"error":{"name":"NotAcceptedError"},"duration":8610},"john.jpvbs.com":{"error":{"name":"NotAcceptedError"},"duration":8819},"someledger.herokuapp.com":{"error":{},"duration":10003}},"hive.dennisappelt.com":{"ilp-kit.michielbdejong.com":{"error":{},"duration":4732},"pineapplesheep.ilp.rocks":{"error":{},"duration":4974},"michiel-is-not-available.herokuapp.com":{"error":{},"duration":5351},"michiel-eur.herokuapp.com":{"error":{},"duration":5934},"best-ilp.herokuapp.com":{"error":{},"duration":7572},"royalcrypto.com":{"error":{},"duration":7865},"someledger.herokuapp.com":{"error":{},"duration":10015},"hive.dennisappelt.com":{"error":{},"duration":15043},"cornelius.sharafian.com":{"error":{},"duration":16771},"john.jpvbs.com":{"error":{},"duration":17967},"nexus.justmoon.com":{"error":{},"duration":18416},"cygnus.vahehovhannisyan.com":{"error":{},"duration":18551},"ggizi.herokuapp.com":{"error":{},"duration":18691}},"ilp-kit.michielbdejong.com":{"pineapplesheep.ilp.rocks":{"error":{},"duration":5098},"royalcrypto.com":{"error":{},"duration":7801},"best-ilp.herokuapp.com":{"error":{},"duration":8064},"michiel-eur.herokuapp.com":{"fee":0.005016046999999947,"duration":9490},"someledger.herokuapp.com":{"error":{},"duration":10013},"ggizi.herokuapp.com":{"fee":-0.05443181929999999,"duration":10892},"ilp-kit.michielbdejong.com":{"error":{},"duration":13857},"hive.dennisappelt.com":{"error":{},"duration":14865},"john.jpvbs.com":{"error":{},"duration":15388},"michiel-is-not-available.herokuapp.com":{"error":{},"duration":15657},"nexus.justmoon.com":{"error":{},"duration":16684},"cygnus.vahehovhannisyan.com":{"error":{},"duration":17464},"cornelius.sharafian.com":{"error":{},"duration":17723}},"john.jpvbs.com":{"ilp-kit.michielbdejong.com":{"error":{},"duration":5197},"pineapplesheep.ilp.rocks":{"error":{},"duration":5377},"michiel-is-not-available.herokuapp.com":{"error":{},"duration":5926},"michiel-eur.herokuapp.com":{"error":{},"duration":6472},"royalcrypto.com":{"error":{},"duration":8296},"best-ilp.herokuapp.com":{"error":{},"duration":8796},"someledger.herokuapp.com":{"error":{},"duration":10009},"hive.dennisappelt.com":{"fee":1,"duration":10874},"ggizi.herokuapp.com":{"fee":1,"duration":13048},"john.jpvbs.com":{"error":{},"duration":15424},"nexus.justmoon.com":{"error":{},"duration":17102},"cornelius.sharafian.com":{"error":{},"duration":17477},"cygnus.vahehovhannisyan.com":{"error":{},"duration":17733}},"cygnus.vahehovhannisyan.com":{"ilp-kit.michielbdejong.com":{"error":{},"duration":5297},"michiel-is-not-available.herokuapp.com":{"error":{},"duration":5655},"pineapplesheep.ilp.rocks":{"error":{},"duration":5661},"michiel-eur.herokuapp.com":{"error":{},"duration":6064},"hive.dennisappelt.com":{"error":{},"duration":6073},"john.jpvbs.com":{"error":{},"duration":6272},"nexus.justmoon.com":{"error":{},"duration":6341},"cornelius.sharafian.com":{"error":{},"duration":6585},"royalcrypto.com":{"error":{},"duration":7348},"ggizi.herokuapp.com":{"error":{},"duration":7544},"best-ilp.herokuapp.com":{"error":{},"duration":7834},"someledger.herokuapp.com":{"error":{},"duration":10005},"cygnus.vahehovhannisyan.com":{"error":{},"duration":15477}},"michiel-is-not-available.herokuapp.com":{"ilp-kit.michielbdejong.com":{"error":{},"duration":5396},"pineapplesheep.ilp.rocks":{"error":{},"duration":5691},"hive.dennisappelt.com":{"error":{},"duration":6112},"cygnus.vahehovhannisyan.com":{"error":{},"duration":6417},"john.jpvbs.com":{"error":{},"duration":6738},"cornelius.sharafian.com":{"error":{},"duration":7697},"ggizi.herokuapp.com":{"error":{},"duration":7749},"royalcrypto.com":{"error":{},"duration":7936},"nexus.justmoon.com":{"error":{},"duration":7953},"best-ilp.herokuapp.com":{"error":{},"duration":8210},"michiel-eur.herokuapp.com":{"fee":0.07034208999999995,"duration":9867},"someledger.herokuapp.com":{"error":{},"duration":10018},"michiel-is-not-available.herokuapp.com":{"error":{},"duration":15068}},"nexus.justmoon.com":{"ilp-kit.michielbdejong.com":{"error":{},"duration":5637},"pineapplesheep.ilp.rocks":{"error":{},"duration":5637},"hive.dennisappelt.com":{"error":{},"duration":6049},"cygnus.vahehovhannisyan.com":{"error":{},"duration":6321},"john.jpvbs.com":{"error":{},"duration":6326},"cornelius.sharafian.com":{"error":{},"duration":6901},"michiel-is-not-available.herokuapp.com":{"error":{},"duration":6967},"michiel-eur.herokuapp.com":{"error":{},"duration":6970},"best-ilp.herokuapp.com":{"error":{},"duration":7579},"ggizi.herokuapp.com":{"error":{},"duration":8129},"royalcrypto.com":{"error":{},"duration":8348},"someledger.herokuapp.com":{"error":{},"duration":10009},"nexus.justmoon.com":{"error":{},"duration":15591}},"cornelius.sharafian.com":{"pineapplesheep.ilp.rocks":{"error":{},"duration":6000},"ilp-kit.michielbdejong.com":{"error":{},"duration":6296},"michiel-is-not-available.herokuapp.com":{"error":{},"duration":6869},"michiel-eur.herokuapp.com":{"error":{},"duration":7168},"hive.dennisappelt.com":{"error":{"name":"NotAcceptedError"},"duration":7653},"royalcrypto.com":{"error":{},"duration":8907},"best-ilp.herokuapp.com":{"error":{},"duration":9321},"someledger.herokuapp.com":{"error":{},"duration":10017},"ggizi.herokuapp.com":{"fee":1,"duration":11986},"cornelius.sharafian.com":{"error":{},"duration":16606},"nexus.justmoon.com":{"error":{},"duration":17604},"cygnus.vahehovhannisyan.com":{"error":{},"duration":17813},"john.jpvbs.com":{"error":{},"duration":18615}},"michiel-eur.herokuapp.com":{"nexus.justmoon.com":{"error":{},"duration":5848},"michiel-is-not-available.herokuapp.com":{"error":{},"duration":6058},"ilp-kit.michielbdejong.com":{"error":{"name":"NotAcceptedError"},"duration":6173},"pineapplesheep.ilp.rocks":{"error":{},"duration":6303},"cygnus.vahehovhannisyan.com":{"error":{},"duration":6664},"john.jpvbs.com":{"error":{},"duration":6974},"hive.dennisappelt.com":{"error":{},"duration":7352},"cornelius.sharafian.com":{"error":{},"duration":7541},"best-ilp.herokuapp.com":{"error":{},"duration":8010},"ggizi.herokuapp.com":{"error":{},"duration":8012},"royalcrypto.com":{"error":{},"duration":8237},"someledger.herokuapp.com":{"error":{},"duration":10001},"michiel-eur.herokuapp.com":{"error":{},"duration":15402}},"ggizi.herokuapp.com":{"ilp-kit.michielbdejong.com":{"error":{},"duration":6777},"pineapplesheep.ilp.rocks":{"error":{},"duration":7084},"michiel-is-not-available.herokuapp.com":{"error":{},"duration":7425},"michiel-eur.herokuapp.com":{"error":{},"duration":7698},"best-ilp.herokuapp.com":{"error":{},"duration":8654},"royalcrypto.com":{"error":{},"duration":8920},"cornelius.sharafian.com":{"error":{"name":"NotAcceptedError"},"duration":9641},"cygnus.vahehovhannisyan.com":{"error":{"name":"NotAcceptedError"},"duration":9913},"john.jpvbs.com":{"error":{"name":"NotAcceptedError"},"duration":9914},"someledger.herokuapp.com":{"error":{},"duration":10002},"ggizi.herokuapp.com":{"error":{},"duration":17228},"hive.dennisappelt.com":{"error":{},"duration":18164},"nexus.justmoon.com":{"error":{},"duration":19563}},"royalcrypto.com":{"ilp-kit.michielbdejong.com":{"error":{},"duration":6934},"michiel-is-not-available.herokuapp.com":{"error":{},"duration":7253},"pineapplesheep.ilp.rocks":{"error":{},"duration":7547},"cygnus.vahehovhannisyan.com":{"error":{},"duration":7840},"hive.dennisappelt.com":{"error":{},"duration":8115},"michiel-eur.herokuapp.com":{"error":{},"duration":8381},"john.jpvbs.com":{"error":{},"duration":8573},"cornelius.sharafian.com":{"error":{},"duration":8925},"ggizi.herokuapp.com":{"error":{},"duration":9004},"nexus.justmoon.com":{"error":{},"duration":9070},"royalcrypto.com":{"error":{"name":"NotAcceptedError"},"duration":9077},"best-ilp.herokuapp.com":{"error":{},"duration":9187},"someledger.herokuapp.com":{"error":{},"duration":10003}},"best-ilp.herokuapp.com":{"ilp-kit.michielbdejong.com":{"error":{},"duration":7277},"pineapplesheep.ilp.rocks":{"error":{},"duration":7635},"michiel-is-not-available.herokuapp.com":{"error":{},"duration":7902},"michiel-eur.herokuapp.com":{"error":{},"duration":8174},"royalcrypto.com":{"error":{},"duration":8813},"best-ilp.herokuapp.com":{"error":{"name":"NotAcceptedError"},"duration":8823},"john.jpvbs.com":{"error":{"name":"NotAcceptedError"},"duration":9140},"someledger.herokuapp.com":{"error":{},"duration":10002},"cornelius.sharafian.com":{"error":{"name":"NotAcceptedError"},"duration":10272},"nexus.justmoon.com":{"error":{"name":"NotAcceptedError"},"duration":10344},"cygnus.vahehovhannisyan.com":{"error":{"name":"NotAcceptedError"},"duration":10351},"hive.dennisappelt.com":{"error":{"name":"NotAcceptedError"},"duration":10359},"ggizi.herokuapp.com":{"error":{"name":"NotAcceptedError"},"duration":11083}},"someledger.herokuapp.com":{"someledger.herokuapp.com":{"error":{},"duration":10000},"ilp-kit.michielbdejong.com":{"error":{},"duration":54265},"pineapplesheep.ilp.rocks":{"error":{},"duration":54610},"michiel-is-not-available.herokuapp.com":{"error":{},"duration":54648},"michiel-eur.herokuapp.com":{"error":{},"duration":54780},"hive.dennisappelt.com":{"error":{},"duration":54792},"john.jpvbs.com":{"error":{},"duration":54806},"cygnus.vahehovhannisyan.com":{"error":{},"duration":54809},"cornelius.sharafian.com":{"error":{},"duration":54992},"nexus.justmoon.com":{"error":{},"duration":55363},"ggizi.herokuapp.com":{"error":{},"duration":55895},"best-ilp.herokuapp.com":{"error":{},"duration":55902},"royalcrypto.com":{"error":{},"duration":56081}}}