{
  "incoming": {
    "hive.dennisappelt.com": {
      "1487602834248": {
        "error": {
          "name": "NotAcceptedError"
        },
        "duration": 5664
      },
      "1487602941495": {
        "error": {},
        "duration": 14681
      },
      "1487602980651": {
        "error": {},
        "duration": 14539
      },
      "1487603006281": {
        "fee": 0,
        "duration": 6380
      },
      "1487603087937": {
        "error": {},
        "duration": 15236
      },
      "1487603167523": {
        "error": {
          "name": "NotAcceptedError"
        },
        "duration": 5330
      },
      "1487603248525": {
        "fee": 0,
        "duration": 7353
      },
      "1487603330600": {
        "fee": 0,
        "duration": 6477
      },
      "1487603411782": {
        "error": {
          "name": "NotAcceptedError"
        },
        "duration": 4856
      },
      "1487603492049": {
        "error": {},
        "duration": 3961
      },
      "1487603573185": {
        "error": {},
        "duration": 3877
      },
      "1487603652944": {
        "error": {},
        "duration": 4056
      },
      "1487603732236": {
        "error": {},
        "duration": 3762
      },
      "1487603812920": {
        "error": {},
        "duration": 3552
      },
      "1487603893272": {
        "error": {},
        "duration": 4250
      },
      "1487603974407": {
        "error": {},
        "duration": 14820
      },
      "1487604054862": {
        "error": {},
        "duration": 4295
      },
      "1487604134122": {
        "fee": 0,
        "duration": 5778
      },
      "1487604214347": {
        "error": {},
        "duration": 3960
      },
      "1487604296109": {
        "error": {
          "name": "NotAcceptedError"
        },
        "duration": 4655
      },
      "1487604376374": {
        "error": {},
        "duration": 4210
      },
      "1487604456583": {
        "error": {},
        "duration": 3707
      }
    },
    "ilp-kit.michielbdejong.com": {
      "1487602834248": {
        "fee": -0.05632296140000003,
        "duration": 6650
      },
      "1487602941495": {
        "error": {},
        "duration": 14767
      },
      "1487602980651": {
        "error": {
          "name": "NotAcceptedError"
        },
        "duration": 4132
      },
      "1487603006281": {
        "error": {},
        "duration": 14208
      },
      "1487603087937": {
        "fee": -0.05632296140000003,
        "duration": 8041
      },
      "1487603167523": {
        "error": {},
        "duration": 15270
      },
      "1487603248525": {
        "fee": -0.05632296140000003,
        "duration": 6290
      },
      "1487603330600": {
        "error": {},
        "duration": 14404
      },
      "1487603411782": {
        "error": {},
        "duration": 14169
      },
      "1487603492049": {
        "error": {
          "name": "NotAcceptedError"
        },
        "duration": 4671
      },
      "1487603573185": {
        "error": {},
        "duration": 14945
      },
      "1487603652944": {
        "error": {
          "name": "NotAcceptedError"
        },
        "duration": 4321
      },
      "1487603732236": {
        "fee": -0.05632295700000005,
        "duration": 5916
      },
      "1487603812920": {
        "error": {
          "name": "NotAcceptedError"
        },
        "duration": 4691
      },
      "1487603893272": {
        "error": {
          "name": "NotAcceptedError"
        },
        "duration": 4231
      },
      "1487603974407": {
        "error": {},
        "duration": 14748
      },
      "1487604054862": {
        "error": {},
        "duration": 14563
      },
      "1487604134122": {
        "fee": -0.05632295700000005,
        "duration": 5383
      },
      "1487604214347": {
        "error": {},
        "duration": 14135
      },
      "1487604296109": {
        "error": {},
        "duration": 13792
      },
      "1487604376374": {
        "error": {
          "name": "NotAcceptedError"
        },
        "duration": 4636
      },
      "1487604456583": {
        "error": {
          "name": "NotAcceptedError"
        },
        "duration": 4718
      }
    },
    "michiel-is-not-available.herokuapp.com": {
      "1487602834248": {
        "error": {},
        "duration": 4436
      },
      "1487602941495": {
        "error": {},
        "duration": 4278
      },
      "1487602980651": {
        "error": {},
        "duration": 4185
      },
      "1487603006281": {
        "error": {},
        "duration": 4597
      },
      "1487603087937": {
        "error": {},
        "duration": 5348
      },
      "1487603167523": {
        "error": {},
        "duration": 4146
      },
      "1487603248525": {
        "error": {},
        "duration": 3629
      },
      "1487603330600": {
        "error": {},
        "duration": 4703
      },
      "1487603411782": {
        "error": {},
        "duration": 4283
      },
      "1487603492049": {
        "error": {},
        "duration": 4326
      },
      "1487603573185": {
        "error": {},
        "duration": 3986
      },
      "1487603652944": {
        "error": {},
        "duration": 4491
      },
      "1487603732236": {
        "error": {},
        "duration": 3743
      },
      "1487603812920": {
        "error": {},
        "duration": 3777
      },
      "1487603893272": {
        "error": {},
        "duration": 4385
      },
      "1487603974407": {
        "error": {},
        "duration": 4613
      },
      "1487604054862": {
        "error": {},
        "duration": 4675
      },
      "1487604134122": {
        "error": {},
        "duration": 3972
      },
      "1487604214347": {
        "error": {},
        "duration": 4181
      },
      "1487604296109": {
        "error": {},
        "duration": 3818
      },
      "1487604376374": {
        "error": {},
        "duration": 4393
      },
      "1487604456583": {
        "error": {},
        "duration": 4160
      }
    },
    "john.jpvbs.com": {
      "1487602834248": {
        "fee": 0,
        "duration": 15552
      },
      "1487602941495": {
        "fee": 0,
        "duration": 14609
      },
      "1487602980651": {
        "error": {
          "name": "NotAcceptedError"
        },
        "duration": 5404
      },
      "1487603006281": {
        "error": {
          "name": "NotAcceptedError"
        },
        "duration": 5400
      },
      "1487603087937": {
        "error": {
          "name": "NotAcceptedError"
        },
        "duration": 6221
      },
      "1487603167523": {
        "error": {
          "name": "NotAcceptedError"
        },
        "duration": 6577
      },
      "1487603248525": {
        "error": {},
        "duration": 15164
      },
      "1487603330600": {
        "error": {
          "name": "NotAcceptedError"
        },
        "duration": 6063
      },
      "1487603411782": {
        "error": {
          "name": "NotAcceptedError"
        },
        "duration": 5230
      },
      "1487603492049": {
        "error": {
          "name": "NotAcceptedError"
        },
        "duration": 5739
      },
      "1487603573185": {
        "error": {
          "name": "NotAcceptedError"
        },
        "duration": 6233
      },
      "1487603652944": {
        "error": {
          "name": "NotAcceptedError"
        },
        "duration": 6021
      },
      "1487603732236": {
        "error": {},
        "duration": 15485
      },
      "1487603812920": {
        "error": {
          "name": "NotAcceptedError"
        },
        "duration": 5794
      },
      "1487603893272": {
        "error": {},
        "duration": 15981
      },
      "1487603974407": {
        "error": {
          "name": "NotAcceptedError"
        },
        "duration": 5828
      },
      "1487604054862": {
        "error": {},
        "duration": 4266
      },
      "1487604134122": {
        "error": {
          "name": "NotAcceptedError"
        },
        "duration": 4799
      },
      "1487604214347": {
        "error": {
          "name": "NotAcceptedError"
        },
        "duration": 6300
      },
      "1487604296109": {
        "error": {},
        "duration": 14705
      },
      "1487604376374": {
        "error": {
          "name": "NotAcceptedError"
        },
        "duration": 5499
      },
      "1487604456583": {
        "error": {
          "name": "NotAcceptedError"
        },
        "duration": 5512
      }
    },
    "michiel-eur.herokuapp.com": {
      "1487602834248": {
        "error": {},
        "duration": 5422
      },
      "1487602941495": {
        "error": {},
        "duration": 4723
      },
      "1487602980651": {
        "error": {},
        "duration": 6280
      },
      "1487603006281": {
        "error": {},
        "duration": 7018
      },
      "1487603087937": {
        "error": {
          "name": "NotAcceptedError"
        },
        "duration": 6272
      },
      "1487603167523": {
        "error": {
          "name": "NotAcceptedError"
        },
        "duration": 5195
      },
      "1487603248525": {
        "error": {
          "name": "NotAcceptedError"
        },
        "duration": 5686
      },
      "1487603330600": {
        "error": {},
        "duration": 15839
      },
      "1487603411782": {
        "error": {},
        "duration": 15065
      },
      "1487603492049": {
        "error": {
          "name": "NotAcceptedError"
        },
        "duration": 5031
      },
      "1487603573185": {
        "error": {
          "name": "NotAcceptedError"
        },
        "duration": 4497
      },
      "1487603652944": {
        "error": {},
        "duration": 14730
      },
      "1487603732236": {
        "error": {
          "name": "NotAcceptedError"
        },
        "duration": 4993
      },
      "1487603812920": {
        "error": {},
        "duration": 14302
      },
      "1487603893272": {
        "error": {},
        "duration": 14512
      },
      "1487603974407": {
        "fee": 0,
        "duration": 6480
      },
      "1487604054862": {
        "error": {
          "name": "NotAcceptedError"
        },
        "duration": 5170
      },
      "1487604134122": {
        "fee": 0,
        "duration": 5448
      },
      "1487604214347": {
        "error": {},
        "duration": 14762
      },
      "1487604296109": {
        "error": {
          "name": "NotAcceptedError"
        },
        "duration": 6209
      },
      "1487604376374": {
        "error": {
          "name": "NotAcceptedError"
        },
        "duration": 4871
      },
      "1487604456583": {
        "error": {
          "name": "NotAcceptedError"
        },
        "duration": 4530
      }
    },
    "cygnus.vahehovhannisyan.com": {
      "1487602834248": {
        "error": {},
        "duration": 4560
      },
      "1487602941495": {
        "error": {},
        "duration": 4996
      },
      "1487602980651": {
        "error": {},
        "duration": 4977
      },
      "1487603006281": {
        "error": {},
        "duration": 4142
      },
      "1487603087937": {
        "error": {},
        "duration": 4537
      },
      "1487603167523": {
        "error": {},
        "duration": 4538
      },
      "1487603248525": {
        "error": {},
        "duration": 3874
      },
      "1487603330600": {
        "error": {},
        "duration": 4883
      },
      "1487603411782": {
        "error": {},
        "duration": 4471
      },
      "1487603492049": {
        "error": {},
        "duration": 4348
      },
      "1487603573185": {
        "error": {},
        "duration": 4062
      },
      "1487603652944": {
        "error": {},
        "duration": 4318
      },
      "1487603732236": {
        "error": {},
        "duration": 4118
      },
      "1487603812920": {
        "error": {},
        "duration": 4010
      },
      "1487603893272": {
        "error": {},
        "duration": 4417
      },
      "1487603974407": {
        "error": {},
        "duration": 4469
      },
      "1487604054862": {
        "error": {},
        "duration": 4481
      },
      "1487604134122": {
        "error": {},
        "duration": 4207
      },
      "1487604214347": {
        "error": {},
        "duration": 4397
      },
      "1487604296109": {
        "error": {},
        "duration": 4016
      },
      "1487604376374": {
        "error": {},
        "duration": 4532
      },
      "1487604456583": {
        "error": {},
        "duration": 4368
      }
    },
    "cornelius.sharafian.com": {
      "1487602834248": {
        "error": {},
        "duration": 14694
      },
      "1487602941495": {
        "error": {},
        "duration": 14959
      },
      "1487602980651": {
        "error": {},
        "duration": 14970
      },
      "1487603006281": {
        "error": {},
        "duration": 14513
      },
      "1487603087937": {
        "error": {},
        "duration": 14832
      },
      "1487603167523": {
        "error": {},
        "duration": 14343
      },
      "1487603248525": {
        "error": {},
        "duration": 14127
      },
      "1487603330600": {
        "error": {},
        "duration": 14616
      },
      "1487603411782": {
        "error": {},
        "duration": 14602
      },
      "1487603492049": {
        "error": {
          "name": "NotAcceptedError"
        },
        "duration": 5435
      },
      "1487603573185": {
        "error": {},
        "duration": 14067
      },
      "1487603652944": {
        "error": {},
        "duration": 14145
      },
      "1487603732236": {
        "error": {},
        "duration": 14355
      },
      "1487603812920": {
        "fee": 0,
        "duration": 4911
      },
      "1487603893272": {
        "error": {},
        "duration": 14834
      },
      "1487603974407": {
        "error": {},
        "duration": 14412
      },
      "1487604054862": {
        "error": {},
        "duration": 14618
      },
      "1487604134122": {
        "fee": 0,
        "duration": 4819
      },
      "1487604214347": {
        "error": {},
        "duration": 14204
      },
      "1487604296109": {
        "error": {
          "name": "NotAcceptedError"
        },
        "duration": 4637
      },
      "1487604376374": {
        "error": {},
        "duration": 14615
      },
      "1487604456583": {
        "error": {},
        "duration": 14137
      }
    },
    "ggizi.herokuapp.com": {
      "1487602834248": {
        "fee": 1,
        "duration": 9615
      },
      "1487602941495": {
        "fee": 1,
        "duration": 14983
      },
      "1487602980651": {
        "error": {},
        "duration": 16100
      },
      "1487603006281": {
        "error": {
          "name": "NotAcceptedError"
        },
        "duration": 7563
      },
      "1487603087937": {
        "error": {},
        "duration": 17431
      },
      "1487603167523": {
        "fee": 1,
        "duration": 10361
      },
      "1487603248525": {
        "error": {},
        "duration": 16480
      },
      "1487603330600": {
        "error": {},
        "duration": 5548
      },
      "1487603411782": {
        "fee": 1,
        "duration": 9361
      },
      "1487603492049": {
        "error": {},
        "duration": 16053
      },
      "1487603573185": {
        "error": {
          "name": "NotAcceptedError"
        },
        "duration": 5784
      },
      "1487603652944": {
        "error": {},
        "duration": 15940
      },
      "1487603732236": {
        "fee": 1,
        "duration": 8430
      },
      "1487603812920": {
        "error": {},
        "duration": 15821
      },
      "1487603893272": {
        "error": {},
        "duration": 16078
      },
      "1487603974407": {
        "error": {
          "name": "NotAcceptedError"
        },
        "duration": 7641
      },
      "1487604054862": {
        "error": {},
        "duration": 5758
      },
      "1487604134122": {
        "error": {},
        "duration": 5095
      },
      "1487604214347": {
        "fee": 1,
        "duration": 8437
      },
      "1487604296109": {
        "fee": 1,
        "duration": 9225
      },
      "1487604376374": {
        "error": {},
        "duration": 14507
      },
      "1487604456583": {
        "error": {
          "name": "NotAcceptedError"
        },
        "duration": 9006
      }
    },
    "nexus.justmoon.com": {
      "1487602834248": {
        "error": {},
        "duration": 14294
      },
      "1487602941495": {
        "error": {},
        "duration": 14304
      },
      "1487602980651": {
        "error": {},
        "duration": 14306
      },
      "1487603006281": {
        "error": {},
        "duration": 14304
      },
      "1487603087937": {
        "error": {},
        "duration": 14189
      },
      "1487603167523": {
        "error": {},
        "duration": 14949
      },
      "1487603248525": {
        "error": {},
        "duration": 14295
      },
      "1487603330600": {
        "error": {},
        "duration": 14384
      },
      "1487603411782": {
        "error": {},
        "duration": 13816
      },
      "1487603492049": {
        "error": {},
        "duration": 14477
      },
      "1487603573185": {
        "error": {},
        "duration": 13750
      },
      "1487603652944": {
        "error": {},
        "duration": 14502
      },
      "1487603732236": {
        "error": {},
        "duration": 13893
      },
      "1487603812920": {
        "error": {},
        "duration": 13696
      },
      "1487603893272": {
        "error": {},
        "duration": 14014
      },
      "1487603974407": {
        "error": {},
        "duration": 14686
      },
      "1487604054862": {
        "error": {},
        "duration": 14613
      },
      "1487604134122": {
        "error": {},
        "duration": 13732
      },
      "1487604214347": {
        "error": {},
        "duration": 14721
      },
      "1487604296109": {
        "error": {},
        "duration": 13902
      },
      "1487604376374": {
        "error": {},
        "duration": 14225
      },
      "1487604456583": {
        "error": {},
        "duration": 13841
      }
    }
  },
  "outgoing": {
    "michiel-is-not-available.herokuapp.com": {
      "1487602834248": {
        "error": {},
        "duration": 4487
      },
      "1487602941495": {
        "error": {},
        "duration": 13877
      },
      "1487602980651": {
        "error": {},
        "duration": 14404
      },
      "1487603006281": {
        "error": {},
        "duration": 4714
      },
      "1487603087937": {
        "error": {
          "name": "NotAcceptedError"
        },
        "duration": 9096
      },
      "1487603167523": {
        "error": {},
        "duration": 4961
      },
      "1487603248525": {
        "error": {},
        "duration": 4343
      },
      "1487603330600": {
        "error": {},
        "duration": 4489
      },
      "1487603411782": {
        "error": {
          "name": "NotAcceptedError"
        },
        "duration": 5955
      },
      "1487603492049": {
        "fee": 1,
        "duration": 7112
      },
      "1487603573185": {
        "error": {},
        "duration": 15160
      },
      "1487603652944": {
        "error": {},
        "duration": 15525
      },
      "1487603732236": {
        "error": {
          "name": "NotAcceptedError"
        },
        "duration": 5621
      },
      "1487603812920": {
        "error": {},
        "duration": 15379
      },
      "1487603893272": {
        "error": {
          "name": "NotAcceptedError"
        },
        "duration": 5778
      },
      "1487603974407": {
        "error": {},
        "duration": 15116
      },
      "1487604054862": {
        "error": {},
        "duration": 4580
      },
      "1487604134122": {
        "error": {},
        "duration": 4258
      },
      "1487604214347": {
        "error": {},
        "duration": 15211
      },
      "1487604296109": {
        "error": {
          "name": "NotAcceptedError"
        },
        "duration": 6136
      },
      "1487604376374": {
        "error": {
          "name": "NotAcceptedError"
        },
        "duration": 6021
      },
      "1487604456583": {
        "error": {},
        "duration": 15618
      }
    },
    "ilp-kit.michielbdejong.com": {
      "1487602834248": {
        "error": {},
        "duration": 4731
      },
      "1487602941495": {
        "error": {},
        "duration": 13355
      },
      "1487602980651": {
        "error": {},
        "duration": 13986
      },
      "1487603006281": {
        "error": {},
        "duration": 4292
      },
      "1487603087937": {
        "error": {
          "name": "NotAcceptedError"
        },
        "duration": 9088
      },
      "1487603167523": {
        "error": {},
        "duration": 4875
      },
      "1487603248525": {
        "error": {},
        "duration": 4462
      },
      "1487603330600": {
        "error": {},
        "duration": 4247
      },
      "1487603411782": {
        "error": {},
        "duration": 15055
      },
      "1487603492049": {
        "error": {},
        "duration": 14618
      },
      "1487603573185": {
        "fee": 1.9999999999999996,
        "duration": 7229
      },
      "1487603652944": {
        "error": {
          "name": "NotAcceptedError"
        },
        "duration": 5623
      },
      "1487603732236": {
        "fee": 1.9999999999999996,
        "duration": 7183
      },
      "1487603812920": {
        "error": {
          "name": "NotAcceptedError"
        },
        "duration": 5900
      },
      "1487603893272": {
        "fee": 1.9999999999999996,
        "duration": 7528
      },
      "1487603974407": {
        "error": {},
        "duration": 15437
      },
      "1487604054862": {
        "error": {},
        "duration": 4818
      },
      "1487604134122": {
        "error": {},
        "duration": 3575
      },
      "1487604214347": {
        "error": {},
        "duration": 15120
      },
      "1487604296109": {
        "error": {
          "name": "NotAcceptedError"
        },
        "duration": 6148
      },
      "1487604376374": {
        "error": {
          "name": "NotAcceptedError"
        },
        "duration": 6029
      },
      "1487604456583": {
        "error": {},
        "duration": 15388
      }
    },
    "michiel-eur.herokuapp.com": {
      "1487602834248": {
        "error": {},
        "duration": 4906
      },
      "1487602941495": {
        "error": {},
        "duration": 13911
      },
      "1487602980651": {
        "error": {},
        "duration": 14948
      },
      "1487603006281": {
        "error": {},
        "duration": 4523
      },
      "1487603087937": {
        "error": {
          "name": "NotAcceptedError"
        },
        "duration": 9084
      },
      "1487603167523": {
        "error": {},
        "duration": 5484
      },
      "1487603248525": {
        "error": {},
        "duration": 5141
      },
      "1487603330600": {
        "error": {},
        "duration": 4982
      },
      "1487603411782": {
        "error": {},
        "duration": 15631
      },
      "1487603492049": {
        "fee": 1,
        "duration": 7510
      },
      "1487603573185": {
        "error": {
          "name": "NotAcceptedError"
        },
        "duration": 5514
      },
      "1487603652944": {
        "error": {},
        "duration": 15672
      },
      "1487603732236": {
        "error": {},
        "duration": 15407
      },
      "1487603812920": {
        "error": {},
        "duration": 15019
      },
      "1487603893272": {
        "error": {},
        "duration": 15833
      },
      "1487603974407": {
        "error": {
          "name": "NotAcceptedError"
        },
        "duration": 6110
      },
      "1487604054862": {
        "error": {},
        "duration": 4953
      },
      "1487604134122": {
        "error": {
          "name": "NotAcceptedError"
        },
        "duration": 5385
      },
      "1487604214347": {
        "error": {
          "name": "NotAcceptedError"
        },
        "duration": 5905
      },
      "1487604296109": {
        "error": {
          "name": "NotAcceptedError"
        },
        "duration": 7570
      },
      "1487604376374": {
        "error": {
          "name": "NotAcceptedError"
        },
        "duration": 6054
      },
      "1487604456583": {
        "error": {
          "name": "NotAcceptedError"
        },
        "duration": 5488
      }
    },
    "hive.dennisappelt.com": {
      "1487602834248": {
        "error": {
          "name": "NotAcceptedError"
        },
        "duration": 5483
      },
      "1487602941495": {
        "error": {},
        "duration": 13750
      },
      "1487602980651": {
        "error": {},
        "duration": 13475
      },
      "1487603006281": {
        "fee": 1,
        "duration": 6329
      },
      "1487603087937": {
        "error": {
          "name": "NotAcceptedError"
        },
        "duration": 8543
      },
      "1487603167523": {
        "error": {},
        "duration": 4808
      },
      "1487603248525": {
        "error": {},
        "duration": 4120
      },
      "1487603330600": {
        "error": {},
        "duration": 4906
      },
      "1487603411782": {
        "error": {
          "name": "NotAcceptedError"
        },
        "duration": 5830
      },
      "1487603492049": {
        "error": {},
        "duration": 14756
      },
      "1487603573185": {
        "fee": 1,
        "duration": 5935
      },
      "1487603652944": {
        "error": {},
        "duration": 14911
      },
      "1487603732236": {
        "fee": 1,
        "duration": 6310
      },
      "1487603812920": {
        "fee": 1,
        "duration": 6713
      },
      "1487603893272": {
        "fee": 1,
        "duration": 6494
      },
      "1487603974407": {
        "error": {},
        "duration": 14917
      },
      "1487604054862": {
        "error": {},
        "duration": 4683
      },
      "1487604134122": {
        "fee": 1,
        "duration": 6504
      },
      "1487604214347": {
        "error": {
          "name": "NotAcceptedError"
        },
        "duration": 5682
      },
      "1487604296109": {
        "error": {},
        "duration": 15585
      },
      "1487604376374": {
        "error": {
          "name": "NotAcceptedError"
        },
        "duration": 6027
      },
      "1487604456583": {
        "fee": 1,
        "duration": 7020
      }
    },
    "john.jpvbs.com": {
      "1487602834248": {
        "error": {
          "name": "NotAcceptedError"
        },
        "duration": 6835
      },
      "1487602941495": {
        "error": {},
        "duration": 14234
      },
      "1487602980651": {
        "error": {},
        "duration": 14433
      },
      "1487603006281": {
        "error": {
          "name": "NotAcceptedError"
        },
        "duration": 5555
      },
      "1487603087937": {
        "error": {
          "name": "NotAcceptedError"
        },
        "duration": 9101
      },
      "1487603167523": {
        "error": {},
        "duration": 5041
      },
      "1487603248525": {
        "error": {},
        "duration": 3966
      },
      "1487603330600": {
        "error": {},
        "duration": 4592
      },
      "1487603411782": {
        "fee": 1,
        "duration": 7296
      },
      "1487603492049": {
        "error": {
          "name": "NotAcceptedError"
        },
        "duration": 5751
      },
      "1487603573185": {
        "error": {},
        "duration": 14732
      },
      "1487603652944": {
        "fee": 1,
        "duration": 8343
      },
      "1487603732236": {
        "error": {
          "name": "NotAcceptedError"
        },
        "duration": 5957
      },
      "1487603812920": {
        "error": {
          "name": "NotAcceptedError"
        },
        "duration": 5294
      },
      "1487603893272": {
        "error": {},
        "duration": 15427
      },
      "1487603974407": {
        "error": {},
        "duration": 14408
      },
      "1487604054862": {
        "error": {},
        "duration": 4903
      },
      "1487604134122": {
        "error": {},
        "duration": 4115
      },
      "1487604214347": {
        "fee": 1,
        "duration": 9255
      },
      "1487604296109": {
        "error": {},
        "duration": 14766
      },
      "1487604376374": {
        "error": {},
        "duration": 15795
      },
      "1487604456583": {
        "fee": 1,
        "duration": 7673
      }
    },
    "ggizi.herokuapp.com": {
      "1487602834248": {
        "fee": 1,
        "duration": 8889
      },
      "1487602941495": {
        "fee": 1,
        "duration": 17509
      },
      "1487602980651": {
        "error": {},
        "duration": 14961
      },
      "1487603006281": {
        "fee": 1,
        "duration": 10154
      },
      "1487603087937": {
        "error": {
          "name": "NotAcceptedError"
        },
        "duration": 9087
      },
      "1487603167523": {
        "error": {},
        "duration": 5291
      },
      "1487603248525": {
        "error": {},
        "duration": 5778
      },
      "1487603330600": {
        "error": {},
        "duration": 5802
      },
      "1487603411782": {
        "error": {},
        "duration": 15902
      },
      "1487603492049": {
        "fee": 1,
        "duration": 8639
      },
      "1487603573185": {
        "error": {},
        "duration": 15729
      },
      "1487603652944": {
        "error": {},
        "duration": 16026
      },
      "1487603732236": {
        "error": {
          "name": "NotAcceptedError"
        },
        "duration": 6269
      },
      "1487603812920": {
        "fee": 1,
        "duration": 7863
      },
      "1487603893272": {
        "error": {},
        "duration": 16459
      },
      "1487603974407": {
        "error": {},
        "duration": 16327
      },
      "1487604054862": {
        "error": {},
        "duration": 5754
      },
      "1487604134122": {
        "error": {},
        "duration": 5688
      },
      "1487604214347": {
        "error": {},
        "duration": 16320
      },
      "1487604296109": {
        "error": {
          "name": "NotAcceptedError"
        },
        "duration": 7543
      },
      "1487604376374": {
        "error": {},
        "duration": 16323
      },
      "1487604456583": {
        "error": {},
        "duration": 16418
      }
    },
    "cornelius.sharafian.com": {
      "1487602834248": {
        "error": {},
        "duration": 14694
      },
      "1487602941495": {
        "error": {},
        "duration": 14959
      },
      "1487602980651": {
        "error": {},
        "duration": 14970
      },
      "1487603006281": {
        "error": {},
        "duration": 14513
      },
      "1487603087937": {
        "error": {},
        "duration": 14832
      },
      "1487603167523": {
        "error": {},
        "duration": 14343
      },
      "1487603248525": {
        "error": {},
        "duration": 14127
      },
      "1487603330600": {
        "error": {},
        "duration": 14616
      },
      "1487603411782": {
        "error": {},
        "duration": 14602
      },
      "1487603492049": {
        "error": {
          "name": "NotAcceptedError"
        },
        "duration": 5435
      },
      "1487603573185": {
        "error": {},
        "duration": 14067
      },
      "1487603652944": {
        "error": {},
        "duration": 14145
      },
      "1487603732236": {
        "error": {},
        "duration": 14355
      },
      "1487603812920": {
        "fee": 0,
        "duration": 4911
      },
      "1487603893272": {
        "error": {},
        "duration": 14834
      },
      "1487603974407": {
        "error": {},
        "duration": 14412
      },
      "1487604054862": {
        "error": {},
        "duration": 14618
      },
      "1487604134122": {
        "fee": 0,
        "duration": 4819
      },
      "1487604214347": {
        "error": {},
        "duration": 14204
      },
      "1487604296109": {
        "error": {
          "name": "NotAcceptedError"
        },
        "duration": 4637
      },
      "1487604376374": {
        "error": {},
        "duration": 14615
      },
      "1487604456583": {
        "error": {},
        "duration": 14137
      }
    },
    "cygnus.vahehovhannisyan.com": {
      "1487602834248": {
        "error": {},
        "duration": 14982
      },
      "1487602941495": {
        "error": {},
        "duration": 24260
      },
      "1487602980651": {
        "error": {},
        "duration": 14642
      },
      "1487603006281": {
        "error": {},
        "duration": 15034
      },
      "1487603087937": {
        "error": {},
        "duration": 17831
      },
      "1487603167523": {
        "error": {
          "name": "NotAcceptedError"
        },
        "duration": 6184
      },
      "1487603248525": {
        "error": {},
        "duration": 14009
      },
      "1487603330600": {
        "error": {
          "name": "NotAcceptedError"
        },
        "duration": 5694
      },
      "1487603411782": {
        "error": {},
        "duration": 14778
      },
      "1487603492049": {
        "error": {
          "name": "NotAcceptedError"
        },
        "duration": 5759
      },
      "1487603573185": {
        "error": {},
        "duration": 15424
      },
      "1487603652944": {
        "error": {
          "name": "NotAcceptedError"
        },
        "duration": 5913
      },
      "1487603732236": {
        "error": {
          "name": "NotAcceptedError"
        },
        "duration": 5347
      },
      "1487603812920": {
        "error": {},
        "duration": 14889
      },
      "1487603893272": {
        "error": {
          "name": "NotAcceptedError"
        },
        "duration": 5024
      },
      "1487603974407": {
        "error": {
          "name": "NotAcceptedError"
        },
        "duration": 5750
      },
      "1487604054862": {
        "error": {
          "name": "NotAcceptedError"
        },
        "duration": 5430
      },
      "1487604134122": {
        "error": {},
        "duration": 15575
      },
      "1487604214347": {
        "error": {},
        "duration": 14982
      },
      "1487604296109": {
        "error": {},
        "duration": 15969
      },
      "1487604376374": {
        "error": {
          "name": "NotAcceptedError"
        },
        "duration": 6023
      },
      "1487604456583": {
        "error": {
          "name": "NotAcceptedError"
        },
        "duration": 5492
      }
    },
    "nexus.justmoon.com": {
      "1487602834248": {
        "error": {},
        "duration": 15435
      },
      "1487602941495": {
        "error": {},
        "duration": 24187
      },
      "1487602980651": {
        "error": {},
        "duration": 14406
      },
      "1487603006281": {
        "error": {},
        "duration": 14929
      },
      "1487603087937": {
        "error": {},
        "duration": 17702
      },
      "1487603167523": {
        "error": {},
        "duration": 15645
      },
      "1487603248525": {
        "error": {},
        "duration": 14199
      },
      "1487603330600": {
        "error": {},
        "duration": 14768
      },
      "1487603411782": {
        "error": {},
        "duration": 14890
      },
      "1487603492049": {
        "error": {
          "name": "NotAcceptedError"
        },
        "duration": 5757
      },
      "1487603573185": {
        "error": {},
        "duration": 14709
      },
      "1487603652944": {
        "error": {},
        "duration": 13867
      },
      "1487603732236": {
        "error": {
          "name": "NotAcceptedError"
        },
        "duration": 5950
      },
      "1487603812920": {
        "error": {
          "name": "NotAcceptedError"
        },
        "duration": 5661
      },
      "1487603893272": {
        "error": {},
        "duration": 14848
      },
      "1487603974407": {
        "error": {
          "name": "NotAcceptedError"
        },
        "duration": 6120
      },
      "1487604054862": {
        "error": {},
        "duration": 14985
      },
      "1487604134122": {
        "error": {},
        "duration": 15420
      },
      "1487604214347": {
        "error": {
          "name": "NotAcceptedError"
        },
        "duration": 5711
      },
      "1487604296109": {
        "error": {},
        "duration": 14133
      },
      "1487604376374": {
        "error": {},
        "duration": 14864
      },
      "1487604456583": {
        "error": {},
        "duration": 15163
      }
    }
  }
}